edgeiq/__init__.py
edgeiq/__init__.pyi
edgeiq/_constants.py
edgeiq/_environment.py
edgeiq/_globals.py
edgeiq/_system_cfg.py
edgeiq/_token_mgmt.py
edgeiq/_trt_support.py
edgeiq/_utils.py
edgeiq/_validate_install.py
edgeiq/_version.py
edgeiq/analytics_services.py
edgeiq/analytics_services.pyi
edgeiq/app_config.py
edgeiq/app_config.pyi
edgeiq/april_tag.py
edgeiq/april_tag.pyi
edgeiq/background_subtractor.py
edgeiq/background_subtractor.pyi
edgeiq/barcode_detection.py
edgeiq/barcode_detection.pyi
edgeiq/base_service.py
edgeiq/base_service.pyi
edgeiq/bounding_box.py
edgeiq/bounding_box.pyi
edgeiq/camera_blockage.py
edgeiq/camera_blockage.pyi
edgeiq/engine_accelerator.py
edgeiq/engine_accelerator.pyi
edgeiq/event_services.py
edgeiq/event_services.pyi
edgeiq/exceptions.py
edgeiq/exceptions.pyi
edgeiq/image_classification.py
edgeiq/image_classification.pyi
edgeiq/instance_segmentation.py
edgeiq/instance_segmentation.pyi
edgeiq/mjpg_video_writer.py
edgeiq/mjpg_video_writer.pyi
edgeiq/pose_estimation.py
edgeiq/pose_estimation.pyi
edgeiq/pose_estimation_pose.py
edgeiq/pose_estimation_pose.pyi
edgeiq/py.typed
edgeiq/qa_services.py
edgeiq/qa_services.pyi
edgeiq/qrcode_detection.py
edgeiq/qrcode_detection.pyi
edgeiq/re_identification.py
edgeiq/re_identification.pyi
edgeiq/realsense.py
edgeiq/realsense.pyi
edgeiq/rtsp_video_writer.py
edgeiq/rtsp_video_writer.pyi
edgeiq/semantic_segmentation.py
edgeiq/semantic_segmentation.pyi
edgeiq/streamer.py
edgeiq/streamer.pyi
edgeiq/video_stream.py
edgeiq/video_stream.pyi
edgeiq/video_writer.py
edgeiq/video_writer.pyi
edgeiq/_production_client/__init__.py
edgeiq/_production_client/constants.py
edgeiq/_production_client/credentials.py
edgeiq/_production_client/production_client.py
edgeiq/_production_client/py.typed
edgeiq/_production_client/util.py
edgeiq/_production_client/clients/__init__.py
edgeiq/_production_client/clients/analytics_cloud_writer.py
edgeiq/_production_client/clients/analytics_file_writer.py
edgeiq-2.8.0.dist-info/METADATA
edgeiq-2.8.0.dist-info/WHEEL
edgeiq-2.8.0.dist-info/top_level.txt
edgeiq-2.8.0.dist-info/RECORD
